<?xml version="1.0" encoding="UTF-8"?>

<COMPONENT> 
  <HEADER AUTHOR="Jan Lolling" COMPATIBILITY="ALL" DATA_AUTO_PROPAGATE="true" HAS_CONDITIONAL_OUTPUTS="false" PLATEFORM="ALL" RELEASE_DATE="20180724" SERIAL="" STARTABLE="true" STATUS="PROD" VERSION="2.0"> 
    <SIGNATURE/> 
  </HEADER>  
  <FAMILIES> 
    <FAMILY>ElasticSearch</FAMILY> 
  </FAMILIES>  
  <DOCUMENTATION> 
    <URL/> 
  </DOCUMENTATION>  
  <CONNECTORS> 
    <CONNECTOR CTYPE="FLOW" MIN_INPUT="0" MAX_INPUT="0" MIN_OUTPUT="0" MAX_OUTPUT="1"/>  
    <CONNECTOR CTYPE="ITERATE" MAX_OUTPUT="1" MAX_INPUT="1"/>  
    <CONNECTOR CTYPE="SUBJOB_OK" MAX_INPUT="1"/>  
    <CONNECTOR CTYPE="SUBJOB_ERROR" MAX_INPUT="1"/>  
    <CONNECTOR CTYPE="COMPONENT_OK"/>  
    <CONNECTOR CTYPE="COMPONENT_ERROR"/>  
    <CONNECTOR CTYPE="RUN_IF"/> 
  </CONNECTORS>  
  <PARAMETERS> 
    <PARAMETER NAME="ELASTIC_COMPONENT" FIELD="COMPONENT_LIST" FILTER="tElasticSearchIndexOutput" NUM_ROW="10" REQUIRED="true"/>  
    <PARAMETER NAME="SCHEMA" FIELD="SCHEMA_TYPE" REQUIRED="true" NUM_ROW="20"> 
      <TABLE READONLY="true"> 
        <COLUMN NAME="key" TYPE="id_Object" READONLY="true" CUSTOM="true" NULLABLE="false" COMMENT="The id of the document"/>  
        <COLUMN NAME="operation" TYPE="id_String" READONLY="true" CUSTOM="true" NULLABLE="true" COMMENT="index, create, delete operation"/>  
        <COLUMN NAME="failure_message" TYPE="id_String" READONLY="true" CUSTOM="true" NULLABLE="true" COMMENT="message in case of failure"/> 
      </TABLE> 
    </PARAMETER>  
    <PARAMETER NAME="CLEAR_ERRORS" FIELD="CHECK" REQUIRED="true" NUM_ROW="30"> 
      <DEFAULT>false</DEFAULT> 
    </PARAMETER> 
  </PARAMETERS>  
  <ADVANCED_PARAMETERS> 
    <PARAMETER NAME="RELEASE_LABEL_20180724" FIELD="LABEL" COLOR="0;0;0" NUM_ROW="900">
      <DEFAULT>Release: 2.0 build at: 20180724</DEFAULT>
    </PARAMETER>
  </ADVANCED_PARAMETERS>  
  <CODEGENERATION> 
    <IMPORTS/> 
  </CODEGENERATION>  
  <RETURNS> 
    <RETURN AVAILABILITY="AFTER" NAME="NB_LINE" TYPE="id_Integer"/>  
    <RETURN AVAILABILITY="FLOW" NAME="COUNT_ERRORS" TYPE="id_Integer"/> 
  </RETURNS>
</COMPONENT>
